synth.pyd
synth-1.0.8.dist-info/DESCRIPTION.rst
synth-1.0.8.dist-info/METADATA
synth-1.0.8.dist-info/metadata.json
synth-1.0.8.dist-info/RECORD
synth-1.0.8.dist-info/top_level.txt
synth-1.0.8.dist-info/WHEEL
synth-1.0.8.dist-info/zip-safe
